CHANGES.txt
LICENSE.txt
MANIFEST.in
PackageInfo.cfg
README.rst
setup.cfg
setup.py
epy-html/api-objects.txt
epy-html/class-tree.html
epy-html/crarr.png
epy-html/epydoc.css
epy-html/epydoc.js
epy-html/frames.html
epy-html/help.html
epy-html/identifier-index.html
epy-html/index.html
epy-html/module-tree.html
epy-html/redirect.html
epy-html/tfasta-module.html
epy-html/tfasta-pysrc.html
epy-html/tfasta._tfasta-module.html
epy-html/tfasta._tfasta-pysrc.html
epy-html/tfasta._version-module.html
epy-html/tfasta._version-pysrc.html
epy-html/tfasta.tfasta_templates-module.html
epy-html/tfasta.tfasta_templates-pysrc.html
epy-html/tfasta.tfasta_templates.FastaTemplate-class.html
epy-html/tfasta.tfasta_templates._t-class.html
epy-html/toc-everything.html
epy-html/toc-tfasta-module.html
epy-html/toc-tfasta._tfasta-module.html
epy-html/toc-tfasta._version-module.html
epy-html/toc-tfasta.tfasta_templates-module.html
epy-html/toc.html
html/genindex.html
html/index.html
html/objects.inv
html/search.html
html/searchindex.js
html/_sources/index.txt
html/_static/ajax-loader.gif
html/_static/basic.css
html/_static/comment-bright.png
html/_static/comment-close.png
html/_static/comment.png
html/_static/default.css
html/_static/doctools.js
html/_static/down-pressed.png
html/_static/down.png
html/_static/file.png
html/_static/jquery.js
html/_static/minus.png
html/_static/plus.png
html/_static/pygments.css
html/_static/searchtools.js
html/_static/sidebar.js
html/_static/underscore.js
html/_static/up-pressed.png
html/_static/up.png
html/_static/websupport.js
test/cytb.fas
test/ovalbumin.fas
test/short-extended.fas
test/tfasta-test
tfasta/__init__.py
tfasta/_tfasta.py
tfasta/_version.py
tfasta/tfasta_templates.py
tfasta.egg-info/PKG-INFO
tfasta.egg-info/SOURCES.txt
tfasta.egg-info/dependency_links.txt
tfasta.egg-info/requires.txt
tfasta.egg-info/top_level.txt