Metadata-Version: 1.1
Name: tfasta
Version: 0.3.2
Summary: Parses fasta files using templates and creates formatted fasta.
Home-page: http://pypi.python.org/pypi/tfasta/
Author: James C. Stroud
Author-email: xtald00d@gmail.com
License: BSD
Keywords: fasta,fasta parser,fasta reader,fasta writer
Platform: UNKNOWN
Classifier: Programming Language :: Python :: 2.6
Classifier: Programming Language :: Python :: 2.7
